_trytrie.abi3.so
.libs_trytrie/libtrie-3a74395d.so
trytrie-1.2.dist-info/METADATA
trytrie-1.2.dist-info/WHEEL
trytrie-1.2.dist-info/top_level.txt
trytrie-1.2.dist-info/RECORD
trytrie/__init__.py
trytrie/_trytrie.c
trytrie/libtrie.so
trytrie/build_trie.py
trytrie/trie.py
trytrie/_trytrie.cpython-36m-x86_64-linux-gnu.so
trytrie/.libs/libtrie-3a74395d.so
