Metadata-Version: 2.1
Name: trytrie
Version: 1.2
Summary: Fast and memory efficient Trie implementation for Python
Home-page: https://github.com/Zamony/trytrie
Author: Nikita Mochalov
Author-email: mochalov.n@yandex.ru
License: UNKNOWN
Platform: UNKNOWN
Classifier: Programming Language :: Python :: 3
Requires-Dist: cffi (>=1.0.0)
